CURRENT_VERSION
LICENSE.txt
MANIFEST.in
README.rst
pytest.ini
requirements.txt
setup.py
autonomie_base/__init__.py
autonomie_base/consts.py
autonomie_base/exception.py
autonomie_base/mail.py
autonomie_base.egg-info/PKG-INFO
autonomie_base.egg-info/SOURCES.txt
autonomie_base.egg-info/dependency_links.txt
autonomie_base.egg-info/entry_points.txt
autonomie_base.egg-info/not-zip-safe
autonomie_base.egg-info/requires.txt
autonomie_base.egg-info/top_level.txt
autonomie_base/models/__init__.py
autonomie_base/models/base.py
autonomie_base/models/initialize.py
autonomie_base/models/mixins.py
autonomie_base/models/types.py
autonomie_base/models/utils.py
autonomie_base/utils/__init__.py
autonomie_base/utils/ascii.py
autonomie_base/utils/csv_tools.py
autonomie_base/utils/date.py
autonomie_base/utils/export.py
autonomie_base/utils/math.py
autonomie_base/utils/renderers.py
autonomie_base/utils/strings.py