Metadata-Version: 2.1
Name: autonomie-base
Version: 4.3.1
Summary: autonomie_base
Home-page: https://github.com/CroissanceCommune/autonomie_celery
Author: Majerti
Author-email: equipe@majerti.fr
License: GPLv3
Keywords: web wsgi bfg pylons pyramid autonomie
Platform: UNKNOWN
Classifier: License :: OSI Approved :: GNU General Public License v3 (GPLv3)
Classifier: Programming Language :: Python
Classifier: Framework :: Pyramid
Classifier: Topic :: Internet :: WWW/HTTP
Classifier: Topic :: Internet :: WWW/HTTP :: WSGI :: Application
Provides-Extra: testing
